klon/__init__.py
klon/build.py
klon/forms.py
klon/html.py
klon/py.typed
klon/text.py
klon/utils.py
klon/version.py
klon/xml.py
klon-2.3.0.dist-info/LICENSE
klon-2.3.0.dist-info/METADATA
klon-2.3.0.dist-info/WHEEL
klon-2.3.0.dist-info/top_level.txt
klon-2.3.0.dist-info/RECORD
