Metadata-Version: 2.1
Name: klon
Version: 2.3.0
Summary: Utilities for building and manipulating ElementTrees
Home-page: https://github.com/saintamh/klon/
Author: Hervé Saint-Amand
Author-email: klon@saintamh.org
Classifier: License :: OSI Approved :: MIT License
Classifier: Operating System :: OS Independent
Classifier: Programming Language :: Python :: 3
Classifier: Topic :: Text Processing :: Markup :: HTML
Classifier: Topic :: Text Processing :: Markup :: XML
License-File: LICENSE
Requires-Dist: lxml <5,>=4
Requires-Dist: lxml-stubs <0.2,>=0.1
Requires-Dist: requests <3,>=2.25
